{"nodes": [{"id": "d_project_manga_reader_ver_2_app_src_main_java_com_example_manga_readerver2_core_utils_filemanager_kt", "label": "FileManager.kt", "file_type": "code", "source_file": "D:\\Project\\Manga-Reader-ver-2\\app\\src\\main\\java\\com\\example\\manga_readerver2\\core\\utils\\FileManager.kt", "source_location": "L1"}, {"id": "utils_filemanager_filemanager", "label": "FileManager", "file_type": "code", "source_file": "D:\\Project\\Manga-Reader-ver-2\\app\\src\\main\\java\\com\\example\\manga_readerver2\\core\\utils\\FileManager.kt", "source_location": "L6"}, {"id": "utils_filemanager_filemanager_getrootpath", "label": ".getRootPath()", "file_type": "code", "source_file": "D:\\Project\\Manga-Reader-ver-2\\app\\src\\main\\java\\com\\example\\manga_readerver2\\core\\utils\\FileManager.kt", "source_location": "L10"}, {"id": "utils_filemanager_filemanager_getdownloadpath", "label": ".getDownloadPath()", "file_type": "code", "source_file": "D:\\Project\\Manga-Reader-ver-2\\app\\src\\main\\java\\com\\example\\manga_readerver2\\core\\utils\\FileManager.kt", "source_location": "L18"}, {"id": "utils_filemanager_filemanager_getmangapath", "label": ".getMangaPath()", "file_type": "code", "source_file": "D:\\Project\\Manga-Reader-ver-2\\app\\src\\main\\java\\com\\example\\manga_readerver2\\core\\utils\\FileManager.kt", "source_location": "L28"}, {"id": "utils_filemanager_filemanager_getchapterpath", "label": ".getChapterPath()", "file_type": "code", "source_file": "D:\\Project\\Manga-Reader-ver-2\\app\\src\\main\\java\\com\\example\\manga_readerver2\\core\\utils\\FileManager.kt", "source_location": "L39"}, {"id": "utils_filemanager_filemanager_getchaptercbzpath", "label": ".getChapterCbzPath()", "file_type": "code", "source_file": "D:\\Project\\Manga-Reader-ver-2\\app\\src\\main\\java\\com\\example\\manga_readerver2\\core\\utils\\FileManager.kt", "source_location": "L48"}, {"id": "utils_filemanager_filemanager_getchapternovelpath", "label": ".getChapterNovelPath()", "file_type": "code", "source_file": "D:\\Project\\Manga-Reader-ver-2\\app\\src\\main\\java\\com\\example\\manga_readerver2\\core\\utils\\FileManager.kt", "source_location": "L56"}, {"id": "utils_filemanager_filemanager_sanitizefilename", "label": ".sanitizeFileName()", "file_type": "code", "source_file": "D:\\Project\\Manga-Reader-ver-2\\app\\src\\main\\java\\com\\example\\manga_readerver2\\core\\utils\\FileManager.kt", "source_location": "L61"}, {"id": "utils_filemanager_filemanager_deletemanga", "label": ".deleteManga()", "file_type": "code", "source_file": "D:\\Project\\Manga-Reader-ver-2\\app\\src\\main\\java\\com\\example\\manga_readerver2\\core\\utils\\FileManager.kt", "source_location": "L65"}, {"id": "utils_filemanager_filemanager_getcachedir", "label": ".getCacheDir()", "file_type": "code", "source_file": "D:\\Project\\Manga-Reader-ver-2\\app\\src\\main\\java\\com\\example\\manga_readerver2\\core\\utils\\FileManager.kt", "source_location": "L69"}, {"id": "utils_filemanager_filemanager_formatbytes", "label": ".formatBytes()", "file_type": "code", "source_file": "D:\\Project\\Manga-Reader-ver-2\\app\\src\\main\\java\\com\\example\\manga_readerver2\\core\\utils\\FileManager.kt", "source_location": "L73"}], "edges": [{"source": "d_project_manga_reader_ver_2_app_src_main_java_com_example_manga_readerver2_core_utils_filemanager_kt", "target": "utils_filemanager_filemanager", "relation": "contains", "confidence": "EXTRACTED", "source_file": "D:\\Project\\Manga-Reader-ver-2\\app\\src\\main\\java\\com\\example\\manga_readerver2\\core\\utils\\FileManager.kt", "source_location": "L6", "weight": 1.0}, {"source": "utils_filemanager_filemanager", "target": "utils_filemanager_filemanager_getrootpath", "relation": "method", "confidence": "EXTRACTED", "source_file": "D:\\Project\\Manga-Reader-ver-2\\app\\src\\main\\java\\com\\example\\manga_readerver2\\core\\utils\\FileManager.kt", "source_location": "L10", "weight": 1.0}, {"source": "utils_filemanager_filemanager", "target": "utils_filemanager_filemanager_getdownloadpath", "relation": "method", "confidence": "EXTRACTED", "source_file": "D:\\Project\\Manga-Reader-ver-2\\app\\src\\main\\java\\com\\example\\manga_readerver2\\core\\utils\\FileManager.kt", "source_location": "L18", "weight": 1.0}, {"source": "utils_filemanager_filemanager", "target": "utils_filemanager_filemanager_getmangapath", "relation": "method", "confidence": "EXTRACTED", "source_file": "D:\\Project\\Manga-Reader-ver-2\\app\\src\\main\\java\\com\\example\\manga_readerver2\\core\\utils\\FileManager.kt", "source_location": "L28", "weight": 1.0}, {"source": "utils_filemanager_filemanager", "target": "utils_filemanager_filemanager_getchapterpath", "relation": "method", "confidence": "EXTRACTED", "source_file": "D:\\Project\\Manga-Reader-ver-2\\app\\src\\main\\java\\com\\example\\manga_readerver2\\core\\utils\\FileManager.kt", "source_location": "L39", "weight": 1.0}, {"source": "utils_filemanager_filemanager", "target": "utils_filemanager_filemanager_getchaptercbzpath", "relation": "method", "confidence": "EXTRACTED", "source_file": "D:\\Project\\Manga-Reader-ver-2\\app\\src\\main\\java\\com\\example\\manga_readerver2\\core\\utils\\FileManager.kt", "source_location": "L48", "weight": 1.0}, {"source": "utils_filemanager_filemanager", "target": "utils_filemanager_filemanager_getchapternovelpath", "relation": "method", "confidence": "EXTRACTED", "source_file": "D:\\Project\\Manga-Reader-ver-2\\app\\src\\main\\java\\com\\example\\manga_readerver2\\core\\utils\\FileManager.kt", "source_location": "L56", "weight": 1.0}, {"source": "utils_filemanager_filemanager", "target": "utils_filemanager_filemanager_sanitizefilename", "relation": "method", "confidence": "EXTRACTED", "source_file": "D:\\Project\\Manga-Reader-ver-2\\app\\src\\main\\java\\com\\example\\manga_readerver2\\core\\utils\\FileManager.kt", "source_location": "L61", "weight": 1.0}, {"source": "utils_filemanager_filemanager", "target": "utils_filemanager_filemanager_deletemanga", "relation": "method", "confidence": "EXTRACTED", "source_file": "D:\\Project\\Manga-Reader-ver-2\\app\\src\\main\\java\\com\\example\\manga_readerver2\\core\\utils\\FileManager.kt", "source_location": "L65", "weight": 1.0}, {"source": "utils_filemanager_filemanager", "target": "utils_filemanager_filemanager_getcachedir", "relation": "method", "confidence": "EXTRACTED", "source_file": "D:\\Project\\Manga-Reader-ver-2\\app\\src\\main\\java\\com\\example\\manga_readerver2\\core\\utils\\FileManager.kt", "source_location": "L69", "weight": 1.0}, {"source": "utils_filemanager_filemanager", "target": "utils_filemanager_filemanager_formatbytes", "relation": "method", "confidence": "EXTRACTED", "source_file": "D:\\Project\\Manga-Reader-ver-2\\app\\src\\main\\java\\com\\example\\manga_readerver2\\core\\utils\\FileManager.kt", "source_location": "L73", "weight": 1.0}, {"source": "utils_filemanager_filemanager_getdownloadpath", "target": "utils_filemanager_filemanager_getrootpath", "relation": "calls", "context": "call", "confidence": "EXTRACTED", "source_file": "D:\\Project\\Manga-Reader-ver-2\\app\\src\\main\\java\\com\\example\\manga_readerver2\\core\\utils\\FileManager.kt", "source_location": "L19", "weight": 1.0}, {"source": "utils_filemanager_filemanager_getmangapath", "target": "utils_filemanager_filemanager_getdownloadpath", "relation": "calls", "context": "call", "confidence": "EXTRACTED", "source_file": "D:\\Project\\Manga-Reader-ver-2\\app\\src\\main\\java\\com\\example\\manga_readerver2\\core\\utils\\FileManager.kt", "source_location": "L29", "weight": 1.0}, {"source": "utils_filemanager_filemanager_getmangapath", "target": "utils_filemanager_filemanager_sanitizefilename", "relation": "calls", "context": "call", "confidence": "EXTRACTED", "source_file": "D:\\Project\\Manga-Reader-ver-2\\app\\src\\main\\java\\com\\example\\manga_readerver2\\core\\utils\\FileManager.kt", "source_location": "L29", "weight": 1.0}, {"source": "utils_filemanager_filemanager_getchapterpath", "target": "utils_filemanager_filemanager_getmangapath", "relation": "calls", "context": "call", "confidence": "EXTRACTED", "source_file": "D:\\Project\\Manga-Reader-ver-2\\app\\src\\main\\java\\com\\example\\manga_readerver2\\core\\utils\\FileManager.kt", "source_location": "L40", "weight": 1.0}, {"source": "utils_filemanager_filemanager_getchapterpath", "target": "utils_filemanager_filemanager_sanitizefilename", "relation": "calls", "context": "call", "confidence": "EXTRACTED", "source_file": "D:\\Project\\Manga-Reader-ver-2\\app\\src\\main\\java\\com\\example\\manga_readerver2\\core\\utils\\FileManager.kt", "source_location": "L40", "weight": 1.0}, {"source": "utils_filemanager_filemanager_getchaptercbzpath", "target": "utils_filemanager_filemanager_getmangapath", "relation": "calls", "context": "call", "confidence": "EXTRACTED", "source_file": "D:\\Project\\Manga-Reader-ver-2\\app\\src\\main\\java\\com\\example\\manga_readerver2\\core\\utils\\FileManager.kt", "source_location": "L49", "weight": 1.0}, {"source": "utils_filemanager_filemanager_getchaptercbzpath", "target": "utils_filemanager_filemanager_sanitizefilename", "relation": "calls", "context": "call", "confidence": "EXTRACTED", "source_file": "D:\\Project\\Manga-Reader-ver-2\\app\\src\\main\\java\\com\\example\\manga_readerver2\\core\\utils\\FileManager.kt", "source_location": "L50", "weight": 1.0}, {"source": "utils_filemanager_filemanager_getchapternovelpath", "target": "utils_filemanager_filemanager_getmangapath", "relation": "calls", "context": "call", "confidence": "EXTRACTED", "source_file": "D:\\Project\\Manga-Reader-ver-2\\app\\src\\main\\java\\com\\example\\manga_readerver2\\core\\utils\\FileManager.kt", "source_location": "L57", "weight": 1.0}, {"source": "utils_filemanager_filemanager_getchapternovelpath", "target": "utils_filemanager_filemanager_sanitizefilename", "relation": "calls", "context": "call", "confidence": "EXTRACTED", "source_file": "D:\\Project\\Manga-Reader-ver-2\\app\\src\\main\\java\\com\\example\\manga_readerver2\\core\\utils\\FileManager.kt", "source_location": "L58", "weight": 1.0}, {"source": "utils_filemanager_filemanager_deletemanga", "target": "utils_filemanager_filemanager_getmangapath", "relation": "calls", "context": "call", "confidence": "EXTRACTED", "source_file": "D:\\Project\\Manga-Reader-ver-2\\app\\src\\main\\java\\com\\example\\manga_readerver2\\core\\utils\\FileManager.kt", "source_location": "L66", "weight": 1.0}], "raw_calls": [{"caller_nid": "utils_filemanager_filemanager_getrootpath", "callee": "File", "is_member_call": false, "source_file": "D:\\Project\\Manga-Reader-ver-2\\app\\src\\main\\java\\com\\example\\manga_readerver2\\core\\utils\\FileManager.kt", "source_location": "L13"}, {"caller_nid": "utils_filemanager_filemanager_getrootpath", "callee": "getExternalFilesDir", "is_member_call": true, "source_file": "D:\\Project\\Manga-Reader-ver-2\\app\\src\\main\\java\\com\\example\\manga_readerver2\\core\\utils\\FileManager.kt", "source_location": "L13"}, {"caller_nid": "utils_filemanager_filemanager_getrootpath", "callee": "exists", "is_member_call": true, "source_file": "D:\\Project\\Manga-Reader-ver-2\\app\\src\\main\\java\\com\\example\\manga_readerver2\\core\\utils\\FileManager.kt", "source_location": "L14"}, {"caller_nid": "utils_filemanager_filemanager_getrootpath", "callee": "mkdirs", "is_member_call": true, "source_file": "D:\\Project\\Manga-Reader-ver-2\\app\\src\\main\\java\\com\\example\\manga_readerver2\\core\\utils\\FileManager.kt", "source_location": "L14"}, {"caller_nid": "utils_filemanager_filemanager_getdownloadpath", "callee": "File", "is_member_call": false, "source_file": "D:\\Project\\Manga-Reader-ver-2\\app\\src\\main\\java\\com\\example\\manga_readerver2\\core\\utils\\FileManager.kt", "source_location": "L19"}, {"caller_nid": "utils_filemanager_filemanager_getdownloadpath", "callee": "exists", "is_member_call": true, "source_file": "D:\\Project\\Manga-Reader-ver-2\\app\\src\\main\\java\\com\\example\\manga_readerver2\\core\\utils\\FileManager.kt", "source_location": "L20"}, {"caller_nid": "utils_filemanager_filemanager_getdownloadpath", "callee": "mkdirs", "is_member_call": true, "source_file": "D:\\Project\\Manga-Reader-ver-2\\app\\src\\main\\java\\com\\example\\manga_readerver2\\core\\utils\\FileManager.kt", "source_location": "L21"}, {"caller_nid": "utils_filemanager_filemanager_getdownloadpath", "callee": "createNewFile", "is_member_call": true, "source_file": "D:\\Project\\Manga-Reader-ver-2\\app\\src\\main\\java\\com\\example\\manga_readerver2\\core\\utils\\FileManager.kt", "source_location": "L23"}, {"caller_nid": "utils_filemanager_filemanager_getdownloadpath", "callee": "File", "is_member_call": false, "source_file": "D:\\Project\\Manga-Reader-ver-2\\app\\src\\main\\java\\com\\example\\manga_readerver2\\core\\utils\\FileManager.kt", "source_location": "L23"}, {"caller_nid": "utils_filemanager_filemanager_getmangapath", "callee": "File", "is_member_call": false, "source_file": "D:\\Project\\Manga-Reader-ver-2\\app\\src\\main\\java\\com\\example\\manga_readerver2\\core\\utils\\FileManager.kt", "source_location": "L29"}, {"caller_nid": "utils_filemanager_filemanager_getmangapath", "callee": "exists", "is_member_call": true, "source_file": "D:\\Project\\Manga-Reader-ver-2\\app\\src\\main\\java\\com\\example\\manga_readerver2\\core\\utils\\FileManager.kt", "source_location": "L30"}, {"caller_nid": "utils_filemanager_filemanager_getmangapath", "callee": "mkdirs", "is_member_call": true, "source_file": "D:\\Project\\Manga-Reader-ver-2\\app\\src\\main\\java\\com\\example\\manga_readerver2\\core\\utils\\FileManager.kt", "source_location": "L30"}, {"caller_nid": "utils_filemanager_filemanager_getmangapath", "callee": "takeLast", "is_member_call": true, "source_file": "D:\\Project\\Manga-Reader-ver-2\\app\\src\\main\\java\\com\\example\\manga_readerver2\\core\\utils\\FileManager.kt", "source_location": "L33"}, {"caller_nid": "utils_filemanager_filemanager_getmangapath", "callee": "File", "is_member_call": false, "source_file": "D:\\Project\\Manga-Reader-ver-2\\app\\src\\main\\java\\com\\example\\manga_readerver2\\core\\utils\\FileManager.kt", "source_location": "L34"}, {"caller_nid": "utils_filemanager_filemanager_getmangapath", "callee": "exists", "is_member_call": true, "source_file": "D:\\Project\\Manga-Reader-ver-2\\app\\src\\main\\java\\com\\example\\manga_readerver2\\core\\utils\\FileManager.kt", "source_location": "L35"}, {"caller_nid": "utils_filemanager_filemanager_getmangapath", "callee": "mkdirs", "is_member_call": true, "source_file": "D:\\Project\\Manga-Reader-ver-2\\app\\src\\main\\java\\com\\example\\manga_readerver2\\core\\utils\\FileManager.kt", "source_location": "L35"}, {"caller_nid": "utils_filemanager_filemanager_getchapterpath", "callee": "File", "is_member_call": false, "source_file": "D:\\Project\\Manga-Reader-ver-2\\app\\src\\main\\java\\com\\example\\manga_readerver2\\core\\utils\\FileManager.kt", "source_location": "L40"}, {"caller_nid": "utils_filemanager_filemanager_getchapterpath", "callee": "exists", "is_member_call": true, "source_file": "D:\\Project\\Manga-Reader-ver-2\\app\\src\\main\\java\\com\\example\\manga_readerver2\\core\\utils\\FileManager.kt", "source_location": "L41"}, {"caller_nid": "utils_filemanager_filemanager_getchapterpath", "callee": "mkdirs", "is_member_call": true, "source_file": "D:\\Project\\Manga-Reader-ver-2\\app\\src\\main\\java\\com\\example\\manga_readerver2\\core\\utils\\FileManager.kt", "source_location": "L41"}, {"caller_nid": "utils_filemanager_filemanager_getchaptercbzpath", "callee": "File", "is_member_call": false, "source_file": "D:\\Project\\Manga-Reader-ver-2\\app\\src\\main\\java\\com\\example\\manga_readerver2\\core\\utils\\FileManager.kt", "source_location": "L50"}, {"caller_nid": "utils_filemanager_filemanager_getchapternovelpath", "callee": "File", "is_member_call": false, "source_file": "D:\\Project\\Manga-Reader-ver-2\\app\\src\\main\\java\\com\\example\\manga_readerver2\\core\\utils\\FileManager.kt", "source_location": "L58"}, {"caller_nid": "utils_filemanager_filemanager_sanitizefilename", "callee": "trim", "is_member_call": true, "source_file": "D:\\Project\\Manga-Reader-ver-2\\app\\src\\main\\java\\com\\example\\manga_readerver2\\core\\utils\\FileManager.kt", "source_location": "L62"}, {"caller_nid": "utils_filemanager_filemanager_sanitizefilename", "callee": "replace", "is_member_call": true, "source_file": "D:\\Project\\Manga-Reader-ver-2\\app\\src\\main\\java\\com\\example\\manga_readerver2\\core\\utils\\FileManager.kt", "source_location": "L62"}, {"caller_nid": "utils_filemanager_filemanager_sanitizefilename", "callee": "Regex", "is_member_call": false, "source_file": "D:\\Project\\Manga-Reader-ver-2\\app\\src\\main\\java\\com\\example\\manga_readerver2\\core\\utils\\FileManager.kt", "source_location": "L62"}, {"caller_nid": "utils_filemanager_filemanager_deletemanga", "callee": "deleteRecursively", "is_member_call": true, "source_file": "D:\\Project\\Manga-Reader-ver-2\\app\\src\\main\\java\\com\\example\\manga_readerver2\\core\\utils\\FileManager.kt", "source_location": "L66"}, {"caller_nid": "utils_filemanager_filemanager_formatbytes", "callee": "format", "is_member_call": true, "source_file": "D:\\Project\\Manga-Reader-ver-2\\app\\src\\main\\java\\com\\example\\manga_readerver2\\core\\utils\\FileManager.kt", "source_location": "L78"}, {"caller_nid": "utils_filemanager_filemanager_formatbytes", "callee": "toDouble", "is_member_call": true, "source_file": "D:\\Project\\Manga-Reader-ver-2\\app\\src\\main\\java\\com\\example\\manga_readerver2\\core\\utils\\FileManager.kt", "source_location": "L78"}, {"caller_nid": "utils_filemanager_filemanager_formatbytes", "callee": "format", "is_member_call": true, "source_file": "D:\\Project\\Manga-Reader-ver-2\\app\\src\\main\\java\\com\\example\\manga_readerver2\\core\\utils\\FileManager.kt", "source_location": "L79"}, {"caller_nid": "utils_filemanager_filemanager_formatbytes", "callee": "toDouble", "is_member_call": true, "source_file": "D:\\Project\\Manga-Reader-ver-2\\app\\src\\main\\java\\com\\example\\manga_readerver2\\core\\utils\\FileManager.kt", "source_location": "L79"}, {"caller_nid": "utils_filemanager_filemanager_formatbytes", "callee": "format", "is_member_call": true, "source_file": "D:\\Project\\Manga-Reader-ver-2\\app\\src\\main\\java\\com\\example\\manga_readerver2\\core\\utils\\FileManager.kt", "source_location": "L80"}, {"caller_nid": "utils_filemanager_filemanager_formatbytes", "callee": "toDouble", "is_member_call": true, "source_file": "D:\\Project\\Manga-Reader-ver-2\\app\\src\\main\\java\\com\\example\\manga_readerver2\\core\\utils\\FileManager.kt", "source_location": "L80"}]}