{"nodes": [{"id": "d_project_manga_reader_ver_2_app_src_main_java_com_example_manga_readerver2_core_download_download_kt", "label": "Download.kt", "file_type": "code", "source_file": "D:\\Project\\Manga-Reader-ver-2\\app\\src\\main\\java\\com\\example\\manga_readerver2\\core\\download\\Download.kt", "source_location": "L1"}, {"id": "download_download_download", "label": "Download", "file_type": "code", "source_file": "D:\\Project\\Manga-Reader-ver-2\\app\\src\\main\\java\\com\\example\\manga_readerver2\\core\\download\\Download.kt", "source_location": "L13"}, {"id": "download_download_state", "label": "State", "file_type": "code", "source_file": "D:\\Project\\Manga-Reader-ver-2\\app\\src\\main\\java\\com\\example\\manga_readerver2\\core\\download\\Download.kt", "source_location": "L55"}], "edges": [{"source": "d_project_manga_reader_ver_2_app_src_main_java_com_example_manga_readerver2_core_download_download_kt", "target": "download_download_download", "relation": "contains", "confidence": "EXTRACTED", "source_file": "D:\\Project\\Manga-Reader-ver-2\\app\\src\\main\\java\\com\\example\\manga_readerver2\\core\\download\\Download.kt", "source_location": "L13", "weight": 1.0}, {"source": "d_project_manga_reader_ver_2_app_src_main_java_com_example_manga_readerver2_core_download_download_kt", "target": "download_download_state", "relation": "contains", "confidence": "EXTRACTED", "source_file": "D:\\Project\\Manga-Reader-ver-2\\app\\src\\main\\java\\com\\example\\manga_readerver2\\core\\download\\Download.kt", "source_location": "L55", "weight": 1.0}], "raw_calls": []}